Tendency_Predict/__init__.py
Tendency_Predict/__version__.py
Tendency_Predict/core.py
Tendency_Predict-0.1.dist-info/LICENSE
Tendency_Predict-0.1.dist-info/METADATA
Tendency_Predict-0.1.dist-info/WHEEL
Tendency_Predict-0.1.dist-info/top_level.txt
Tendency_Predict-0.1.dist-info/RECORD
