Metadata-Version: 2.1
Name: Tendency-Predict
Version: 0.1
Summary: Use  cubic exponential smoothing to predict.
Home-page: https://pypi.org/project/My-Toolbox-zhaozl/
Author: zhaozl
Author-email: 545362989@qq.com
License: MIT
Platform: UNKNOWN
Classifier: License :: OSI Approved :: MIT License
Classifier: Programming Language :: Python
Classifier: Programming Language :: Python :: 3
Classifier: Programming Language :: Python :: 3.6
Classifier: Programming Language :: Python :: Implementation :: CPython
Classifier: Programming Language :: Python :: Implementation :: PyPy
Requires-Python: >=3.7.0
